ytclip_server/__init__.py
ytclip_server/app.py
ytclip_server/index.html
ytclip_server/version.py
ytclip_server-1.0.4.dist-info/LICENSE
ytclip_server-1.0.4.dist-info/METADATA
ytclip_server-1.0.4.dist-info/WHEEL
ytclip_server-1.0.4.dist-info/entry_points.txt
ytclip_server-1.0.4.dist-info/top_level.txt
ytclip_server-1.0.4.dist-info/RECORD
