Metadata-Version: 2.1
Name: ytclip-server
Version: 1.0.4
Summary: Server to run ytclip.
Home-page: https://github.com/zackees/ytclip-server
Author: Zach Vorhies
Author-email: dont@email.me
License: MIT
Platform: UNKNOWN
Classifier: License :: OSI Approved :: MIT License
Classifier: Programming Language :: Python :: 3.6
Classifier: Programming Language :: Python :: 3.9
Classifier: Operating System :: Microsoft :: Windows
Classifier: Operating System :: POSIX
Classifier: Operating System :: MacOS :: MacOS X
Classifier: Environment :: Console
Requires-Python: >=3.6.0
Requires-Dist: flask
Requires-Dist: ytclip
Requires-Dist: flask-executor
Provides-Extra: test
Requires-Dist: pytest ; extra == 'test'
